lexia/README.md
lexia/__init__.py
lexia/api_client.py
lexia/centrifugo_client.py
lexia/dev_stream_client.py
lexia/models.py
lexia/requirements.txt
lexia/response_handler.py
lexia/unified_handler.py
lexia/utils.py
lexia/web/__init__.py
lexia/web/app_factory.py
lexia/web/endpoints.py
lexia-1.2.13.dist-info/licenses/LICENSE
lexia-1.2.13.dist-info/METADATA
lexia-1.2.13.dist-info/WHEEL
lexia-1.2.13.dist-info/top_level.txt
lexia-1.2.13.dist-info/RECORD
