Metadata-Version: 2.4
Name: lexia
Version: 1.2.13
Summary: Clean, minimal package for Lexia platform integration
Home-page: https://github.com/Xalantico/lexia-pip
Author: Lexia Team
Author-email: Lexia Team <support@lexiaplatform.com>
Maintainer-email: Lexia Team <support@lexiaplatform.com>
License-Expression: MIT
Project-URL: Homepage, https://github.com/Xalantico/lexia-pip
Project-URL: Documentation, https://github.com/Xalantico/lexia-pip#readme
Project-URL: Repository, https://github.com/Xalantico/lexia-pip
Project-URL: Bug Tracker, https://github.com/Xalantico/lexia-pip/issues
Keywords: lexia,ai,chatbot,platform,integration,fastapi,real-time
Classifier: Development Status :: 4 - Beta
Classifier: Intended Audience :: Developers
Classifier: Operating System :: OS Independent
Classifier: Programming Language :: Python :: 3
Classifier: Programming Language :: Python :: 3.8
Classifier: Programming Language :: Python :: 3.9
Classifier: Programming Language :: Python :: 3.10
Classifier: Programming Language :: Python :: 3.11
Classifier: Programming Language :: Python :: 3.12
Classifier: Programming Language :: Python :: 3.13
Classifier: Topic :: Software Development :: Libraries :: Python Modules
Classifier: Topic :: Communications :: Chat
Classifier: Topic :: Internet :: WWW/HTTP :: HTTP Servers
Classifier: Framework :: FastAPI
Requires-Python: >=3.8
License-File: LICENSE
Requires-Dist: requests>=2.25.0
Requires-Dist: pydantic>=2.0.0
Provides-Extra: web
Requires-Dist: fastapi>=0.100.0; extra == "web"
Requires-Dist: uvicorn>=0.20.0; extra == "web"
Provides-Extra: dev
Requires-Dist: pytest>=6.0; extra == "dev"
Requires-Dist: pytest-asyncio>=0.18.0; extra == "dev"
Requires-Dist: black>=21.0; extra == "dev"
Requires-Dist: flake8>=3.8; extra == "dev"
Requires-Dist: mypy>=0.800; extra == "dev"
Dynamic: author
Dynamic: home-page
Dynamic: license-file
Dynamic: requires-python
